{"cameraMode":{"drawMode":0,"name":"Shaded","section":"Shading Mode"},"sceneLighting":false,"audioPlay":false,"sceneViewState":{"showFog":true,"showMaterialUpdate":false,"showSkybox":false,"showFlares":true,"showImageEffects":true,"showParticleSystems":true},"in2DMode":false,"pivot":{"x":-0.5441593527793884,"y":-18.650680541992189,"z":-8.018075942993164},"rotation":{"x":-0.020345095545053483,"y":0.8904657959938049,"z":-0.4530715346336365,"w":-0.0383119098842144},"size":17.534343719482423,"orthographic":false}